azure/mgmt/avs/__init__.py
azure/mgmt/avs/_client.py
azure/mgmt/avs/_configuration.py
azure/mgmt/avs/_patch.py
azure/mgmt/avs/_validation.py
azure/mgmt/avs/_version.py
azure/mgmt/avs/py.typed
azure/mgmt/avs/_utils/__init__.py
azure/mgmt/avs/_utils/model_base.py
azure/mgmt/avs/_utils/serialization.py
azure/mgmt/avs/aio/__init__.py
azure/mgmt/avs/aio/_client.py
azure/mgmt/avs/aio/_configuration.py
azure/mgmt/avs/aio/_patch.py
azure/mgmt/avs/aio/operations/__init__.py
azure/mgmt/avs/aio/operations/_operations.py
azure/mgmt/avs/aio/operations/_patch.py
azure/mgmt/avs/models/__init__.py
azure/mgmt/avs/models/_enums.py
azure/mgmt/avs/models/_models.py
azure/mgmt/avs/models/_patch.py
azure/mgmt/avs/operations/__init__.py
azure/mgmt/avs/operations/_operations.py
azure/mgmt/avs/operations/_patch.py
azure_mgmt_avs-10.0.0.dist-info/licenses/LICENSE
azure_mgmt_avs-10.0.0.dist-info/METADATA
azure_mgmt_avs-10.0.0.dist-info/WHEEL
azure_mgmt_avs-10.0.0.dist-info/top_level.txt
azure_mgmt_avs-10.0.0.dist-info/RECORD
